{
    "last_update": "2026-07-24 22:53",
    "spot": 2.09,
    "data": [
        {
            "date": "2026-08-21",
            "max_pain": 2.5,
            "call_oi": 4572,
            "put_oi": 838,
            "pc_ratio": 0.1833,
            "is_monthly": true
        },
        {
            "date": "2026-09-18",
            "max_pain": 2.0,
            "call_oi": 98,
            "put_oi": 31,
            "pc_ratio": 0.3163,
            "is_monthly": true
        },
        {
            "date": "2026-11-20",
            "max_pain": 3.0,
            "call_oi": 1242,
            "put_oi": 585,
            "pc_ratio": 0.471,
            "is_monthly": true
        },
        {
            "date": "2027-01-15",
            "max_pain": 2.5,
            "call_oi": 10673,
            "put_oi": 2226,
            "pc_ratio": 0.2086,
            "is_monthly": true
        }
    ]
}