{
    "last_update": "2026-07-08 06:53",
    "spot": 402.9,
    "data": [
        {
            "date": "2026-07-08",
            "max_pain": 410.0,
            "call_oi": 128789,
            "put_oi": 59927,
            "pc_ratio": 0.4653,
            "is_monthly": false
        },
        {
            "date": "2026-07-10",
            "max_pain": 400.0,
            "call_oi": 229485,
            "put_oi": 234751,
            "pc_ratio": 1.0229,
            "is_monthly": false
        },
        {
            "date": "2026-07-13",
            "max_pain": 410.0,
            "call_oi": 14400,
            "put_oi": 9270,
            "pc_ratio": 0.6438,
            "is_monthly": false
        },
        {
            "date": "2026-07-15",
            "max_pain": 415.0,
            "call_oi": 14605,
            "put_oi": 8006,
            "pc_ratio": 0.5482,
            "is_monthly": true
        },
        {
            "date": "2026-07-17",
            "max_pain": 400.0,
            "call_oi": 405986,
            "put_oi": 297202,
            "pc_ratio": 0.732,
            "is_monthly": true
        },
        {
            "date": "2026-07-20",
            "max_pain": 410.0,
            "call_oi": 1027,
            "put_oi": 1046,
            "pc_ratio": 1.0185,
            "is_monthly": true
        },
        {
            "date": "2026-07-24",
            "max_pain": 400.0,
            "call_oi": 46659,
            "put_oi": 34465,
            "pc_ratio": 0.7387,
            "is_monthly": false
        },
        {
            "date": "2026-07-31",
            "max_pain": 400.0,
            "call_oi": 41564,
            "put_oi": 28810,
            "pc_ratio": 0.6931,
            "is_monthly": false
        },
        {
            "date": "2026-08-07",
            "max_pain": 400.0,
            "call_oi": 26752,
            "put_oi": 10192,
            "pc_ratio": 0.381,
            "is_monthly": false
        },
        {
            "date": "2026-08-14",
            "max_pain": 435.0,
            "call_oi": 3264,
            "put_oi": 2310,
            "pc_ratio": 0.7077,
            "is_monthly": false
        },
        {
            "date": "2026-08-21",
            "max_pain": 395.0,
            "call_oi": 193800,
            "put_oi": 155179,
            "pc_ratio": 0.8007,
            "is_monthly": true
        },
        {
            "date": "2026-09-18",
            "max_pain": 400.0,
            "call_oi": 256260,
            "put_oi": 202348,
            "pc_ratio": 0.7896,
            "is_monthly": true
        },
        {
            "date": "2026-10-16",
            "max_pain": 400.0,
            "call_oi": 74037,
            "put_oi": 77035,
            "pc_ratio": 1.0405,
            "is_monthly": true
        },
        {
            "date": "2026-11-20",
            "max_pain": 400.0,
            "call_oi": 97094,
            "put_oi": 107982,
            "pc_ratio": 1.1121,
            "is_monthly": true
        },
        {
            "date": "2026-12-18",
            "max_pain": 350.0,
            "call_oi": 336837,
            "put_oi": 306720,
            "pc_ratio": 0.9106,
            "is_monthly": true
        }
    ]
}